functions_by_nomadstalker/README.md
functions_by_nomadstalker/math_funcitons.py
functions_by_nomadstalker-0.3.0.dist-info/WHEEL
functions_by_nomadstalker-0.3.0.dist-info/METADATA
functions_by_nomadstalker-0.3.0.dist-info/RECORD
